telecom/__init__.py
telecom/telecom.so
telecom/.libs/libtelecom-d71b0a20.so
telecom_py-0.0.4.dist-info/WHEEL
telecom_py-0.0.4.dist-info/top_level.txt
telecom_py-0.0.4.dist-info/METADATA
telecom_py-0.0.4.dist-info/RECORD
