Metadata-Version: 2.1
Name: telecom-py
Version: 0.0.4
Summary: Discord voice client
Home-page: https://github.com/b1naryth1ef/telecom
Author: b1nzy
Author-email: b1naryth1ef@gmail.com
License: UNKNOWN
Platform: UNKNOWN
Classifier: Topic :: Internet
Classifier: Topic :: Software Development :: Libraries
Classifier: Topic :: Software Development :: Libraries :: Python Modules
Classifier: Topic :: Utilities
Classifier: Programming Language :: C
Classifier: Programming Language :: Python :: 2
Classifier: Programming Language :: Python :: 2.7
Classifier: Programming Language :: Python :: 3
Classifier: Programming Language :: Python :: 3.5
Classifier: Programming Language :: Python :: 3.6
Classifier: Programming Language :: Python :: 3.7
Requires-Python: >=2.7, !=3.0.*, !=3.1.*, !=3.2.*, !=3.3.*, !=3.4.*
